{"cameraMode":{"drawMode":0,"name":"Shaded","section":"Shading Mode"},"sceneLighting":true,"audioPlay":false,"sceneViewState":{"showFog":true,"showMaterialUpdate":false,"showSkybox":true,"showFlares":true,"showImageEffects":true,"showParticleSystems":true,"showVisualEffectGraphs":true,"m_FxEnabled":true},"in2DMode":false,"pivot":{"x":6.740080833435059,"y":-2.4993515014648439,"z":-1.7854061126708985},"rotation":{"x":-0.027757257223129274,"y":0.899768054485321,"z":-0.4316559135913849,"w":-0.05784023553133011},"size":16.646364212036134,"orthographic":false}